LICENSE
MANIFEST.in
README.md
pyproject.toml
setup.cfg
setup.py
src/cypack/__init__.py
src/cypack/functions.cpp
src/cypack/functions.h
src/cypack/generate_doc.py
src/cypack/rego.pyx
src/rego.egg-info/PKG-INFO
src/rego.egg-info/SOURCES.txt
src/rego.egg-info/dependency_links.txt
src/rego.egg-info/not-zip-safe
src/rego.egg-info/requires.txt
src/rego.egg-info/top_level.txt