Metadata-Version: 2.1
Name: rego
Version: 1.6.1
Summary: Automatic Time Series Forecasting and Missing Value Imputation
Home-page: https://channelattribution.io/rego
Author: Davide Altomare, David Loris
Author-email: info@channelattribution.io
License: UNKNOWN
Project-URL: Documentation, https://channelattribution.io/rego
Project-URL: Code, https://github.com/DavideAltomare/rego
Project-URL: Issue tracker, https://github.com/DavideAltomare/rego/issues
Platform: UNKNOWN
Classifier: Development Status :: 5 - Production/Stable
Classifier: Intended Audience :: Education
Classifier: Intended Audience :: Science/Research
Classifier: Topic :: Scientific/Engineering
Classifier: Topic :: Scientific/Engineering :: Mathematics
Classifier: Natural Language :: English
Classifier: Operating System :: OS Independent
Classifier: Programming Language :: C++
Classifier: Programming Language :: Cython
Classifier: Programming Language :: Python
Classifier: Programming Language :: Python :: 3
Classifier: Programming Language :: Python :: 3.4
Classifier: Programming Language :: Python :: 3.5
Classifier: Programming Language :: Python :: 3.6
Classifier: Programming Language :: Python :: 3.7
Classifier: Programming Language :: Python :: 3 :: Only
Classifier: Programming Language :: Python :: Implementation :: CPython
Requires-Python: >=3.4
License-File: LICENSE
